authguard/__init__.py
authguard/client.py
authguard/crypto.py
authguard_py-1.0.4.dist-info/licenses/LICENSE
authguard_py-1.0.4.dist-info/METADATA
authguard_py-1.0.4.dist-info/WHEEL
authguard_py-1.0.4.dist-info/top_level.txt
authguard_py-1.0.4.dist-info/RECORD
