Metadata-Version: 2.4
Name: authguard-py
Version: 1.0.4
Summary: AuthGuard Python SDK - Secure authentication client with NaCl encryption
Author-email: Evora <support@evora.lol>
License: MIT
Project-URL: Homepage, https://evora.lol
Project-URL: Documentation, https://evora.lol/docs
Project-URL: Repository, https://github.com/valiant-chicken/evora
Keywords: authentication,security,nacl,encryption,sdk
Classifier: Development Status :: 4 - Beta
Classifier: Intended Audience :: Developers
Classifier: License :: OSI Approved :: MIT License
Classifier: Operating System :: OS Independent
Classifier: Programming Language :: Python :: 3
Classifier: Programming Language :: Python :: 3.8
Classifier: Programming Language :: Python :: 3.9
Classifier: Programming Language :: Python :: 3.10
Classifier: Programming Language :: Python :: 3.11
Classifier: Programming Language :: Python :: 3.12
Classifier: Topic :: Security
Classifier: Topic :: Software Development :: Libraries :: Python Modules
Requires-Python: >=3.8
License-File: LICENSE
Requires-Dist: pynacl>=1.5.0
Requires-Dist: requests>=2.31.0
Provides-Extra: dev
Requires-Dist: pytest>=7.0; extra == "dev"
Requires-Dist: pytest-cov>=4.0; extra == "dev"
Requires-Dist: black>=23.0; extra == "dev"
Requires-Dist: mypy>=1.0; extra == "dev"
Dynamic: license-file
